<?xml version="1.0" encoding="UTF-8"?>
<?xml-stylesheet type="text/xsl" href="default.xsl"?>
<fr:tree xmlns:fr="http://www.jonmsterling.com/jms-005P.xml" root="false">
  <fr:frontmatter>
    <fr:authors>
      <fr:author>
        <fr:link href="trebor.xml" title="Trebor" addr="trebor" type="local">Trebor</fr:link>
      </fr:author>
    </fr:authors>
    <fr:date>
      <fr:year>2024</fr:year>
      <fr:month>3</fr:month>
      <fr:day>6</fr:day>
    </fr:date>
    <fr:anchor>2948</fr:anchor>
    <fr:addr type="user">algm-000P</fr:addr>
    <fr:route>algm-000P.xml</fr:route>
    <fr:title text="Value of section at a point">Value of section at a point</fr:title>
    <fr:taxon>Definition</fr:taxon>
  </fr:frontmatter>
  <fr:mainmatter>
    <fr:p>Given a <fr:link href="algm-000L.xml" title="Locally ringed space" addr="algm-000L" type="local">locally ringed space</fr:link> and a section <fr:tex display="inline"><![CDATA[f \in  \Gamma (U, \mathscr {O})]]></fr:tex>, the germ of <fr:tex display="inline"><![CDATA[f]]></fr:tex> at a point is an element of a local ring. The image of this element in the residue field, i.e. the quotient by the unique maximal ideal is called the <fr:strong>value</fr:strong> of this section at this point.</fr:p>
  </fr:mainmatter>
  <fr:backmatter>
    <fr:tree show-metadata="false" hidden-when-empty="true">
      <fr:frontmatter>
        <fr:anchor>2941</fr:anchor>
        <fr:title text="References">References</fr:title>
      </fr:frontmatter>
      <fr:mainmatter />
    </fr:tree>
    <fr:tree show-metadata="false" hidden-when-empty="true">
      <fr:frontmatter>
        <fr:anchor>2942</fr:anchor>
        <fr:title text="Context">Context</fr:title>
      </fr:frontmatter>
      <fr:mainmatter />
    </fr:tree>
    <fr:tree show-metadata="false" hidden-when-empty="true">
      <fr:frontmatter>
        <fr:anchor>2944</fr:anchor>
        <fr:title text="Backlinks">Backlinks</fr:title>
      </fr:frontmatter>
      <fr:mainmatter>
        <fr:tree show-metadata="true" expanded="false" toc="false" numbered="false">
          <fr:frontmatter>
            <fr:authors>
              <fr:author>
                <fr:link href="trebor.xml" title="Trebor" addr="trebor" type="local">Trebor</fr:link>
              </fr:author>
            </fr:authors>
            <fr:date>
              <fr:year>2024</fr:year>
              <fr:month>3</fr:month>
              <fr:day>6</fr:day>
            </fr:date>
            <fr:source-path>/Users/trebor/Desktop/blog/forest/trees/algm-000O.tree</fr:source-path>
            <fr:anchor>2943</fr:anchor>
            <fr:addr type="user">algm-000O</fr:addr>
            <fr:route>algm-000O.xml</fr:route>
            <fr:title text="Locally ringed space">Locally ringed space</fr:title>
            <fr:taxon>Intuition</fr:taxon>
          </fr:frontmatter>
          <fr:mainmatter>
            <fr:p>The <fr:link href="algm-000L.xml" title="Locally ringed space" addr="algm-000L" type="local">locality</fr:link> requirement for a <fr:link href="algm-000M.xml" title="Ringed space" addr="algm-000M" type="local">ringed space</fr:link> is to guarantee that the sections behave like functions valued in some field.</fr:p>
            <fr:p>It is impossible in general to discuss the vanishing region of a section <fr:tex display="inline"><![CDATA[f \in  \Gamma (U, \mathscr {O})]]></fr:tex>. For instance, the germs of continuous functions are non-zero on their support, which is the closure of the non-vanishing region. In algebraic geometry, such an overspill destroys most valuable information. We can talk about the maximal region on which the section is invertible, but this is different from being non-zero if sections don’t behave like functions. Similarly, it is also impossible to discuss the value of a section at some point in general. In locally ringed space, we have <fr:link href="algm-000P.xml" title="Value of section at a point" addr="algm-000P" type="local">Definition <fr:contextual-number addr="algm-000P" /></fr:link>.</fr:p>
          </fr:mainmatter>
        </fr:tree>
      </fr:mainmatter>
    </fr:tree>
    <fr:tree show-metadata="false" hidden-when-empty="true">
      <fr:frontmatter>
        <fr:anchor>2946</fr:anchor>
        <fr:title text="Related">Related</fr:title>
      </fr:frontmatter>
      <fr:mainmatter>
        <fr:tree show-metadata="true" expanded="false" toc="false" numbered="false">
          <fr:frontmatter>
            <fr:authors>
              <fr:author>
                <fr:link href="trebor.xml" title="Trebor" addr="trebor" type="local">Trebor</fr:link>
              </fr:author>
            </fr:authors>
            <fr:date>
              <fr:year>2024</fr:year>
              <fr:month>3</fr:month>
              <fr:day>5</fr:day>
            </fr:date>
            <fr:source-path>/Users/trebor/Desktop/blog/forest/trees/algm-000L.tree</fr:source-path>
            <fr:anchor>2945</fr:anchor>
            <fr:addr type="user">algm-000L</fr:addr>
            <fr:route>algm-000L.xml</fr:route>
            <fr:title text="Locally ringed space">Locally ringed space</fr:title>
            <fr:taxon>Definition</fr:taxon>
          </fr:frontmatter>
          <fr:mainmatter>
            <fr:p>Given a <fr:link href="algm-000M.xml" title="Ringed space" addr="algm-000M" type="local">ringed space</fr:link>, i.e. a space <fr:tex display="inline"><![CDATA[X]]></fr:tex> with a sheaf of rings <fr:tex display="inline"><![CDATA[\mathscr {O}]]></fr:tex>, it is said to be <fr:strong>locally ringed</fr:strong> iff the following conditions hold.</fr:p>
            <fr:ul><fr:li>If <fr:tex display="inline"><![CDATA[\Gamma (U, \mathscr {O}) = 0]]></fr:tex>, then <fr:tex display="inline"><![CDATA[U]]></fr:tex> is empty.</fr:li>
  <fr:li>Suppose <fr:tex display="inline"><![CDATA[f + g \in  \Gamma (U, \mathscr {O})]]></fr:tex> is invertible, then we can cover <fr:tex display="inline"><![CDATA[U]]></fr:tex> with two open sets such that <fr:tex display="inline"><![CDATA[f]]></fr:tex> and <fr:tex display="inline"><![CDATA[g]]></fr:tex> are invertible when restricted respectively.</fr:li></fr:ul>
            <fr:p>This can be unified as one condition: If a finite sum in <fr:tex display="inline"><![CDATA[\Gamma (U, \mathscr {O})]]></fr:tex> is invertible, then each summand is invertible when restricted to an open, which jointly covers <fr:tex display="inline"><![CDATA[U]]></fr:tex>.</fr:p>
          </fr:mainmatter>
        </fr:tree>
      </fr:mainmatter>
    </fr:tree>
    <fr:tree show-metadata="false" hidden-when-empty="true">
      <fr:frontmatter>
        <fr:anchor>2947</fr:anchor>
        <fr:title text="Contributions">Contributions</fr:title>
      </fr:frontmatter>
      <fr:mainmatter />
    </fr:tree>
  </fr:backmatter>
</fr:tree>
