<?xml version="1.0" encoding="UTF-8"?>
<?xml-stylesheet type="text/xsl" href="default.xsl"?>
<fr:tree
toc="true"
numbered="true"
show-heading="true"
show-metadata="true"
expanded="true"
root="false"
xmlns:fr="http://www.jonmsterling.com/jms-005P.xml"><fr:frontmatter><fr:anchor>837</fr:anchor><fr:addr
type="machine">#268</fr:addr><fr:route>unstable-268.xml</fr:route><fr:taxon>Proof</fr:taxon><fr:date><fr:year>2024</fr:year><fr:month>8</fr:month><fr:day>22</fr:day></fr:date><fr:authors><fr:author><fr:link
type="local"
href="trebor.xml"
addr="trebor"
title="Trebor">Trebor</fr:link></fr:author></fr:authors><fr:parent>algm-001Z</fr:parent></fr:frontmatter><fr:mainmatter>
  <fr:p>We just need to prove the <fr:link
type="local"
href="algm-001Y.xml"
addr="algm-001Y"
title="Affinification">affinification</fr:link> is not an isomorphism. Consider the global sections of the <fr:link
type="local"
href="algm-000M.xml"
addr="algm-000M"
title="Ringed space">structure sheaf</fr:link>, which comes from the pullback of <fr:tex
display="inline"><![CDATA[\mathbb {C}[x, y, x^{-1}]]]></fr:tex> and <fr:tex
display="inline"><![CDATA[\mathbb {C}[x, y, y^{-1}]]]></fr:tex> over <fr:tex
display="inline"><![CDATA[\mathbb {C}[x, y, x^{-1}, y^{-1}]]]></fr:tex>. The result is simply <fr:tex
display="inline"><![CDATA[\mathbb {C}[x, y]]]></fr:tex>. We can compute that the affinification map is the inclusion map into <fr:tex
display="inline"><![CDATA[\mathbb {A}_{\mathbb {C}}^2]]></fr:tex>. This cannot be an isomorphism because the underlying space is different.</fr:p>
</fr:mainmatter><fr:backmatter><fr:tree
toc="false"
numbered="false"
show-heading="true"
show-metadata="false"
expanded="true"
root="false"
xmlns:fr="http://www.jonmsterling.com/jms-005P.xml"><fr:frontmatter><fr:title
text="Context">Context</fr:title><fr:authors /></fr:frontmatter><fr:mainmatter><fr:tree
toc="true"
numbered="false"
show-heading="true"
show-metadata="true"
expanded="false"
root="false"
xmlns:fr="http://www.jonmsterling.com/jms-005P.xml"><fr:frontmatter><fr:anchor>839</fr:anchor><fr:addr
type="user">algm-001Z</fr:addr><fr:route>algm-001Z.xml</fr:route><fr:title
text="A non-affine scheme">A non-affine scheme</fr:title><fr:taxon>Example</fr:taxon><fr:date><fr:year>2024</fr:year><fr:month>8</fr:month><fr:day>22</fr:day></fr:date><fr:authors><fr:author><fr:link
type="local"
href="trebor.xml"
addr="trebor"
title="Trebor">Trebor</fr:link></fr:author></fr:authors></fr:frontmatter><fr:mainmatter><fr:p>The open subscheme of <fr:tex
display="inline"><![CDATA[\mathbb {A}_{\mathbb {C}}^2 = \operatorname {Spec} \mathbb {C}[x, y]]]></fr:tex> given by removing the origin, or equivalently the open <fr:tex
display="inline"><![CDATA[D(x) \cup  D(y)]]></fr:tex>, is not <fr:link
type="local"
href="algm-000Q.xml"
addr="algm-000Q"
title="Affine scheme">affine</fr:link>.</fr:p>
  
    
    <fr:tree
toc="false"
numbered="true"
show-heading="true"
show-metadata="false"
expanded="true"
root="false"
xmlns:fr="http://www.jonmsterling.com/jms-005P.xml"><fr:frontmatter><fr:anchor>831</fr:anchor><fr:addr
type="machine">#268</fr:addr><fr:route>unstable-268.xml</fr:route><fr:taxon>Proof</fr:taxon><fr:date><fr:year>2024</fr:year><fr:month>8</fr:month><fr:day>22</fr:day></fr:date><fr:authors><fr:author><fr:link
type="local"
href="trebor.xml"
addr="trebor"
title="Trebor">Trebor</fr:link></fr:author></fr:authors><fr:parent>algm-001Z</fr:parent></fr:frontmatter><fr:mainmatter>
  <fr:p>We just need to prove the <fr:link
type="local"
href="algm-001Y.xml"
addr="algm-001Y"
title="Affinification">affinification</fr:link> is not an isomorphism. Consider the global sections of the <fr:link
type="local"
href="algm-000M.xml"
addr="algm-000M"
title="Ringed space">structure sheaf</fr:link>, which comes from the pullback of <fr:tex
display="inline"><![CDATA[\mathbb {C}[x, y, x^{-1}]]]></fr:tex> and <fr:tex
display="inline"><![CDATA[\mathbb {C}[x, y, y^{-1}]]]></fr:tex> over <fr:tex
display="inline"><![CDATA[\mathbb {C}[x, y, x^{-1}, y^{-1}]]]></fr:tex>. The result is simply <fr:tex
display="inline"><![CDATA[\mathbb {C}[x, y]]]></fr:tex>. We can compute that the affinification map is the inclusion map into <fr:tex
display="inline"><![CDATA[\mathbb {A}_{\mathbb {C}}^2]]></fr:tex>. This cannot be an isomorphism because the underlying space is different.</fr:p>
</fr:mainmatter><fr:backmatter /></fr:tree>
  
</fr:mainmatter><fr:backmatter /></fr:tree></fr:mainmatter><fr:backmatter /></fr:tree></fr:backmatter></fr:tree>