<?xml version="1.0" encoding="UTF-8"?>
<?xml-stylesheet type="text/xsl" href="default.xsl"?>
<fr:tree xmlns:fr="http://www.jonmsterling.com/jms-005P.xml" root="false">
  <fr:frontmatter>
    <fr:authors>
      <fr:author>
        <fr:link href="trebor.xml" title="Trebor" addr="trebor" type="local">Trebor</fr:link>
      </fr:author>
    </fr:authors>
    <fr:date>
      <fr:year>2024</fr:year>
      <fr:month>2</fr:month>
      <fr:day>18</fr:day>
    </fr:date>
    <fr:anchor>1306</fr:anchor>
    <fr:addr type="machine">unstable/405</fr:addr>
    <fr:route>unstable-405.xml</fr:route>
    <fr:title text="Additive category › "><fr:link href="hmlg-000P.xml" title="Additive category" addr="hmlg-000P" type="local">Additive category</fr:link> › </fr:title>
    <fr:taxon>Proof</fr:taxon>
  </fr:frontmatter>
  <fr:mainmatter>
  <fr:p>By the universal property of products and coproducts, a map from the coproduct of some objects <fr:tex display="inline"><![CDATA[X_i]]></fr:tex> to their product is given by a matrix of morphisms <fr:tex display="inline"><![CDATA[f_{ij} : X_i \to  X_j]]></fr:tex>. We choose the identity matrix
    <fr:tex display="block"><![CDATA[f_{ij} = \begin {cases}
      \textrm {id} & (i = j) \\
      0 & (i \ne  j)
    \end {cases}]]></fr:tex>
    where <fr:tex display="inline"><![CDATA[0]]></fr:tex> is the additive neutral element in the abelian group <fr:tex display="inline"><![CDATA[\hom (X_i, X_j)]]></fr:tex>. This gives a canonical map <fr:tex display="inline"><![CDATA[\coprod _i X_i \to  \prod _i X_i]]></fr:tex>.</fr:p>

  <fr:p>When there are finitely many objects involved, we can construct an inverse. Consider the morphisms <fr:tex display="block"><![CDATA[\prod _i X_i \xrightarrow {\pi _j} X_j \xrightarrow {\iota _j} \coprod _i X_i.]]></fr:tex> We claim the sum of these morphisms is the desired inverse. To verify this, we compose them. Using bilinearity, we are reduced to showing that the coproduct and product of the identity map is the identity, which is true.</fr:p>
</fr:mainmatter>
  <fr:backmatter>
    <fr:tree show-metadata="false" hidden-when-empty="true">
      <fr:frontmatter>
        <fr:anchor>1300</fr:anchor>
        <fr:title text="References">References</fr:title>
      </fr:frontmatter>
      <fr:mainmatter />
    </fr:tree>
    <fr:tree show-metadata="false" hidden-when-empty="true">
      <fr:frontmatter>
        <fr:anchor>1302</fr:anchor>
        <fr:title text="Context">Context</fr:title>
      </fr:frontmatter>
      <fr:mainmatter>
        <fr:tree show-metadata="true" expanded="false" toc="false" numbered="false">
          <fr:frontmatter>
            <fr:authors>
              <fr:author>
                <fr:link href="trebor.xml" title="Trebor" addr="trebor" type="local">Trebor</fr:link>
              </fr:author>
            </fr:authors>
            <fr:date>
              <fr:year>2024</fr:year>
              <fr:month>2</fr:month>
              <fr:day>18</fr:day>
            </fr:date>
            <fr:source-path>/Users/trebor/Desktop/blog/forest/trees/hmlg-000P.tree</fr:source-path>
            <fr:anchor>1301</fr:anchor>
            <fr:addr type="user">hmlg-000P</fr:addr>
            <fr:route>hmlg-000P.xml</fr:route>
            <fr:title text="Additive category">Additive category</fr:title>
            <fr:taxon>Definition</fr:taxon>
          </fr:frontmatter>
          <fr:mainmatter><fr:p>Let <fr:tex display="inline"><![CDATA[\mathcal {C}]]></fr:tex> be <fr:link href="hmlg-000O.xml" title="\mathsf{Ab}-enriched category" addr="hmlg-000O" type="local"><fr:tex display="inline"><![CDATA[\mathsf {Ab}]]></fr:tex>-enriched</fr:link>. The finite products and coproducts, if they exist, are isomorphic via a canonical map. If they all exist, then this category is called an <fr:strong>additive category</fr:strong>. In particular, the nullary product and coproduct coincide, and we call the object <fr:strong>zero object</fr:strong>, denoted <fr:tex display="inline"><![CDATA[0]]></fr:tex>.</fr:p>
  
    
    <fr:tree show-metadata="false" toc="false"><fr:frontmatter><fr:authors><fr:author><fr:link href="trebor.xml" title="Trebor" addr="trebor" type="local">Trebor</fr:link></fr:author></fr:authors><fr:date><fr:year>2024</fr:year><fr:month>2</fr:month><fr:day>18</fr:day></fr:date><fr:source-path>/Users/trebor/Desktop/blog/forest/trees/hmlg-000P.tree</fr:source-path><fr:anchor>607</fr:anchor><fr:addr type="machine">unstable/405</fr:addr><fr:route>unstable-405.xml</fr:route><fr:title text="" /><fr:taxon>Proof</fr:taxon></fr:frontmatter><fr:mainmatter>
  <fr:p>By the universal property of products and coproducts, a map from the coproduct of some objects <fr:tex display="inline"><![CDATA[X_i]]></fr:tex> to their product is given by a matrix of morphisms <fr:tex display="inline"><![CDATA[f_{ij} : X_i \to  X_j]]></fr:tex>. We choose the identity matrix
    <fr:tex display="block"><![CDATA[f_{ij} = \begin {cases}
      \textrm {id} & (i = j) \\
      0 & (i \ne  j)
    \end {cases}]]></fr:tex>
    where <fr:tex display="inline"><![CDATA[0]]></fr:tex> is the additive neutral element in the abelian group <fr:tex display="inline"><![CDATA[\hom (X_i, X_j)]]></fr:tex>. This gives a canonical map <fr:tex display="inline"><![CDATA[\coprod _i X_i \to  \prod _i X_i]]></fr:tex>.</fr:p>

  <fr:p>When there are finitely many objects involved, we can construct an inverse. Consider the morphisms <fr:tex display="block"><![CDATA[\prod _i X_i \xrightarrow {\pi _j} X_j \xrightarrow {\iota _j} \coprod _i X_i.]]></fr:tex> We claim the sum of these morphisms is the desired inverse. To verify this, we compose them. Using bilinearity, we are reduced to showing that the coproduct and product of the identity map is the identity, which is true.</fr:p>
</fr:mainmatter></fr:tree>
  
</fr:mainmatter>
        </fr:tree>
      </fr:mainmatter>
    </fr:tree>
    <fr:tree show-metadata="false" hidden-when-empty="true">
      <fr:frontmatter>
        <fr:anchor>1303</fr:anchor>
        <fr:title text="Backlinks">Backlinks</fr:title>
      </fr:frontmatter>
      <fr:mainmatter />
    </fr:tree>
    <fr:tree show-metadata="false" hidden-when-empty="true">
      <fr:frontmatter>
        <fr:anchor>1304</fr:anchor>
        <fr:title text="Related">Related</fr:title>
      </fr:frontmatter>
      <fr:mainmatter />
    </fr:tree>
    <fr:tree show-metadata="false" hidden-when-empty="true">
      <fr:frontmatter>
        <fr:anchor>1305</fr:anchor>
        <fr:title text="Contributions">Contributions</fr:title>
      </fr:frontmatter>
      <fr:mainmatter />
    </fr:tree>
  </fr:backmatter>
</fr:tree>
